LICENSE.txt
MANIFEST.in
README.md
setup.cfg
setup.py
clim/__init__.py
clim/clim.py
clim.egg-info/PKG-INFO
clim.egg-info/SOURCES.txt
clim.egg-info/dependency_links.txt
clim.egg-info/entry_points.txt
clim.egg-info/top_level.txt