Metadata-Version: 2.1
Name: clim
Version: 1.0.2
Summary: CoLumn IMproved
Home-page: https://github.com/coelias/clim
Author: Carlos del Ojo Elias
Author-email: deepbit@gmail.com
License: GPLv3
Keywords: csv tsv column human-readable dataset
Platform: UNKNOWN
Classifier: Development Status :: 5 - Production/Stable
Classifier: Topic :: Scientific/Engineering :: Information Analysis
Classifier: Topic :: Scientific/Engineering :: Bio-Informatics
Classifier: License :: OSI Approved :: GNU General Public License v3 (GPLv3)
Classifier: Programming Language :: Python :: 2
Classifier: Programming Language :: Python :: 3
Classifier: Intended Audience :: Science/Research
Classifier: Environment :: Console
